cli.py
maven_version.py
mvn_compare-1.0.dist-info/LICENSE
mvn_compare-1.0.dist-info/METADATA
mvn_compare-1.0.dist-info/WHEEL
mvn_compare-1.0.dist-info/entry_points.txt
mvn_compare-1.0.dist-info/top_level.txt
mvn_compare-1.0.dist-info/RECORD
