Metadata-Version: 2.1
Name: mvn-compare
Version: 1.0
Summary: Compare maven release versions
Home-page: https://github.com/suru33/maven-version-comparator
Author: SuRu
Author-email: 33urus@gmail.com
License: GPLv3+
Platform: UNKNOWN
Classifier: Development Status :: 5 - Production/Stable
Classifier: Environment :: Console
Classifier: Intended Audience :: Developers
Classifier: Natural Language :: English
Classifier: License :: OSI Approved :: GNU General Public License v3 or later (GPLv3+)
Classifier: Operating System :: OS Independent
Classifier: Programming Language :: Python
Classifier: Topic :: Software Development :: Libraries
Requires-Python: >=3.6
